{
  "updatedAt": "2026-06-29T22:58:06.280Z",
  "results": {
    "1": {
      "homeScore": 2,
      "awayScore": 0,
      "status": "finished"
    },
    "2": {
      "homeScore": 2,
      "awayScore": 1,
      "status": "finished"
    },
    "3": {
      "homeScore": 1,
      "awayScore": 1,
      "status": "finished"
    },
    "4": {
      "homeScore": 4,
      "awayScore": 1,
      "status": "finished"
    },
    "5": {
      "homeScore": 2,
      "awayScore": 0,
      "status": "finished"
    },
    "6": {
      "homeScore": 1,
      "awayScore": 1,
      "status": "finished"
    },
    "7": {
      "homeScore": 1,
      "awayScore": 1,
      "status": "finished"
    },
    "8": {
      "homeScore": 0,
      "awayScore": 1,
      "status": "finished"
    },
    "9": {
      "homeScore": 7,
      "awayScore": 1,
      "status": "finished"
    },
    "10": {
      "homeScore": 2,
      "awayScore": 2,
      "status": "finished"
    },
    "11": {
      "homeScore": 1,
      "awayScore": 0,
      "status": "finished"
    },
    "12": {
      "homeScore": 5,
      "awayScore": 1,
      "status": "finished"
    },
    "13": {
      "homeScore": 0,
      "awayScore": 0,
      "status": "finished"
    },
    "14": {
      "homeScore": 1,
      "awayScore": 1,
      "status": "finished"
    },
    "15": {
      "homeScore": 1,
      "awayScore": 1,
      "status": "finished"
    },
    "16": {
      "homeScore": 2,
      "awayScore": 2,
      "status": "finished"
    },
    "17": {
      "homeScore": 3,
      "awayScore": 1,
      "status": "finished"
    },
    "18": {
      "homeScore": 1,
      "awayScore": 4,
      "status": "finished"
    },
    "19": {
      "homeScore": 3,
      "awayScore": 0,
      "status": "finished"
    },
    "20": {
      "homeScore": 3,
      "awayScore": 1,
      "status": "finished"
    },
    "21": {
      "homeScore": 1,
      "awayScore": 1,
      "status": "finished"
    },
    "22": {
      "homeScore": 4,
      "awayScore": 2,
      "status": "finished"
    },
    "23": {
      "homeScore": 1,
      "awayScore": 0,
      "status": "finished"
    },
    "24": {
      "homeScore": 1,
      "awayScore": 3,
      "status": "finished"
    },
    "25": {
      "homeScore": 1,
      "awayScore": 1,
      "status": "finished"
    },
    "26": {
      "homeScore": 4,
      "awayScore": 1,
      "status": "finished"
    },
    "27": {
      "homeScore": 6,
      "awayScore": 0,
      "status": "finished"
    },
    "28": {
      "homeScore": 1,
      "awayScore": 0,
      "status": "finished"
    },
    "29": {
      "homeScore": 2,
      "awayScore": 0,
      "status": "finished"
    },
    "30": {
      "homeScore": 0,
      "awayScore": 1,
      "status": "finished"
    },
    "31": {
      "homeScore": 3,
      "awayScore": 0,
      "status": "finished"
    },
    "32": {
      "homeScore": 0,
      "awayScore": 1,
      "status": "finished"
    },
    "33": {
      "homeScore": 5,
      "awayScore": 1,
      "status": "finished"
    },
    "34": {
      "homeScore": 2,
      "awayScore": 1,
      "status": "finished"
    },
    "35": {
      "homeScore": 0,
      "awayScore": 0,
      "status": "finished"
    },
    "36": {
      "homeScore": 0,
      "awayScore": 4,
      "status": "finished"
    },
    "37": {
      "homeScore": 4,
      "awayScore": 0,
      "status": "finished"
    },
    "38": {
      "homeScore": 0,
      "awayScore": 0,
      "status": "finished"
    },
    "39": {
      "homeScore": 2,
      "awayScore": 2,
      "status": "finished"
    },
    "40": {
      "homeScore": 1,
      "awayScore": 3,
      "status": "finished"
    },
    "41": {
      "homeScore": 2,
      "awayScore": 0,
      "status": "finished"
    },
    "42": {
      "homeScore": 3,
      "awayScore": 0,
      "status": "finished"
    },
    "43": {
      "homeScore": 3,
      "awayScore": 2,
      "status": "finished"
    },
    "44": {
      "homeScore": 1,
      "awayScore": 2,
      "status": "finished"
    },
    "45": {
      "homeScore": 5,
      "awayScore": 0,
      "status": "finished"
    },
    "46": {
      "homeScore": 0,
      "awayScore": 0,
      "status": "finished"
    },
    "47": {
      "homeScore": 0,
      "awayScore": 1,
      "status": "finished"
    },
    "48": {
      "homeScore": 1,
      "awayScore": 0,
      "status": "finished"
    },
    "49": {
      "homeScore": 2,
      "awayScore": 1,
      "status": "finished"
    },
    "50": {
      "homeScore": 3,
      "awayScore": 1,
      "status": "finished"
    },
    "51": {
      "homeScore": 0,
      "awayScore": 3,
      "status": "finished"
    },
    "52": {
      "homeScore": 4,
      "awayScore": 2,
      "status": "finished"
    },
    "53": {
      "homeScore": 0,
      "awayScore": 3,
      "status": "finished"
    },
    "54": {
      "homeScore": 1,
      "awayScore": 0,
      "status": "finished"
    },
    "55": {
      "homeScore": 0,
      "awayScore": 2,
      "status": "finished"
    },
    "56": {
      "homeScore": 2,
      "awayScore": 1,
      "status": "finished"
    },
    "57": {
      "homeScore": 1,
      "awayScore": 1,
      "status": "finished"
    },
    "58": {
      "homeScore": 1,
      "awayScore": 3,
      "status": "finished"
    },
    "59": {
      "homeScore": 3,
      "awayScore": 2,
      "status": "finished"
    },
    "60": {
      "homeScore": 0,
      "awayScore": 0,
      "status": "finished"
    },
    "61": {
      "homeScore": 1,
      "awayScore": 4,
      "status": "finished"
    },
    "62": {
      "homeScore": 5,
      "awayScore": 0,
      "status": "finished"
    },
    "63": {
      "homeScore": 0,
      "awayScore": 0,
      "status": "finished"
    },
    "64": {
      "homeScore": 0,
      "awayScore": 1,
      "status": "finished"
    },
    "65": {
      "homeScore": 1,
      "awayScore": 1,
      "status": "finished"
    },
    "66": {
      "homeScore": 1,
      "awayScore": 5,
      "status": "finished"
    },
    "67": {
      "homeScore": 0,
      "awayScore": 2,
      "status": "finished"
    },
    "68": {
      "homeScore": 2,
      "awayScore": 1,
      "status": "finished"
    },
    "69": {
      "homeScore": 0,
      "awayScore": 0,
      "status": "finished"
    },
    "70": {
      "homeScore": 3,
      "awayScore": 1,
      "status": "finished"
    },
    "71": {
      "homeScore": 1,
      "awayScore": 3,
      "status": "finished"
    },
    "72": {
      "homeScore": 3,
      "awayScore": 3,
      "status": "finished"
    }
  }
}
